phantomconfig/__init__.py
phantomconfig/generators.py
phantomconfig/parsers.py
phantomconfig/phantomconfig.py
phantomconfig/__pycache__/__init__.cpython-39.pyc
phantomconfig/__pycache__/generators.cpython-39.pyc
phantomconfig/__pycache__/parsers.cpython-39.pyc
phantomconfig/__pycache__/phantomconfig.cpython-39.pyc
phantomconfig-0.3.4.dist-info/LICENSE
phantomconfig-0.3.4.dist-info/METADATA
phantomconfig-0.3.4.dist-info/WHEEL
phantomconfig-0.3.4.dist-info/top_level.txt
phantomconfig-0.3.4.dist-info/RECORD
